nkwa_pay_sdk/__init__.py
nkwa_pay_sdk/_hooks/__init__.py
nkwa_pay_sdk/_hooks/registration.py
nkwa_pay_sdk/_hooks/sdkhooks.py
nkwa_pay_sdk/_hooks/types.py
nkwa_pay_sdk/_version.py
nkwa_pay_sdk/basesdk.py
nkwa_pay_sdk/httpclient.py
nkwa_pay_sdk/models/__init__.py
nkwa_pay_sdk/models/apierror.py
nkwa_pay_sdk/models/availability.py
nkwa_pay_sdk/models/get_payments_id_op.py
nkwa_pay_sdk/models/httperror.py
nkwa_pay_sdk/models/payment.py
nkwa_pay_sdk/models/paymentrequest.py
nkwa_pay_sdk/models/paymentstatus.py
nkwa_pay_sdk/models/paymenttype.py
nkwa_pay_sdk/models/security.py
nkwa_pay_sdk/models/telecomoperator.py
nkwa_pay_sdk/payments.py
nkwa_pay_sdk/py.typed
nkwa_pay_sdk/sdk.py
nkwa_pay_sdk/sdkconfiguration.py
nkwa_pay_sdk/service.py
nkwa_pay_sdk/types/__init__.py
nkwa_pay_sdk/types/basemodel.py
nkwa_pay_sdk/utils/__init__.py
nkwa_pay_sdk/utils/annotations.py
nkwa_pay_sdk/utils/datetimes.py
nkwa_pay_sdk/utils/enums.py
nkwa_pay_sdk/utils/eventstreaming.py
nkwa_pay_sdk/utils/forms.py
nkwa_pay_sdk/utils/headers.py
nkwa_pay_sdk/utils/logger.py
nkwa_pay_sdk/utils/metadata.py
nkwa_pay_sdk/utils/queryparams.py
nkwa_pay_sdk/utils/requestbodies.py
nkwa_pay_sdk/utils/retries.py
nkwa_pay_sdk/utils/security.py
nkwa_pay_sdk/utils/serializers.py
nkwa_pay_sdk/utils/url.py
nkwa_pay_sdk/utils/values.py
nkwa_pay_sdk-0.3.0.dist-info/METADATA
nkwa_pay_sdk-0.3.0.dist-info/WHEEL
nkwa_pay_sdk-0.3.0.dist-info/RECORD
